zenopay/__init__.py
zenopay-0.1.1.dist-info/LICENCE
zenopay-0.1.1.dist-info/METADATA
zenopay-0.1.1.dist-info/WHEEL
zenopay-0.1.1.dist-info/top_level.txt
zenopay-0.1.1.dist-info/RECORD
