Metadata-Version: 2.1
Name: zenopay
Version: 0.1.1
Summary: A Python wrapper for ZenoPay Payment API.
Home-page: https://github.com/jovyinny/zenopay
Author: Jovine Mutelani
Author-email: jovinerobotics@gmail.com
License: MIT
Project-URL: Bug Tracker, https://github.com/jovyinny/zenopay/issues
Project-URL: Documentation, https://jovyinny.github.io/zenopay/
Project-URL: Source Code, https://github.com/jovyinny/zenopay
Keywords: zenopay,zenopay SDK,zeno pay SDK,ZenoPay Wrapper
Classifier: Development Status :: 3 - Alpha
Classifier: Intended Audience :: Developers
Classifier: Topic :: Software Development :: Libraries :: Python Modules
Classifier: License :: OSI Approved :: MIT License
Classifier: Programming Language :: Python :: 3.7
Classifier: Programming Language :: Python :: 3.8
Classifier: Programming Language :: Python :: 3.9
Classifier: Programming Language :: Python :: 3.10
Classifier: Programming Language :: Python :: 3.11
Requires-Python: >=3.7
License-File: LICENCE
Requires-Dist: requests
Requires-Dist: phonenumbers
